saltriverprojectenergyapi/__init__.py
saltriverprojectenergyapi/client.py
saltriverprojectenergyapi/const.py
saltriverprojectenergyapi/objects/hourly_usage.py
saltriverprojectenergyapi/objects/weather_data.py
saltriverprojectenergyapi-1.0.1.dist-info/METADATA
saltriverprojectenergyapi-1.0.1.dist-info/WHEEL
saltriverprojectenergyapi-1.0.1.dist-info/licenses/LICENSE
saltriverprojectenergyapi-1.0.1.dist-info/RECORD
