Metadata-Version: 2.4
Name: saltriverprojectenergyapi
Version: 1.0.1
Summary: Unofficial api for the Arizona Salt River Project (SRP) API
Project-URL: Homepage, https://github.com/tehdave/SaltRiverProjectEnergyAPI
Project-URL: Issues, https://github.com/tehdave/SaltRiverProjectEnergyAPI/issues
Author-email: Dave Rich <drich@nea-online.net>
License-File: LICENSE
Classifier: Operating System :: OS Independent
Classifier: Programming Language :: Python :: 3
Requires-Python: >=3.8
Requires-Dist: requests
